README.rst
setup.py
suds_jurko_requests.egg-info/PKG-INFO
suds_jurko_requests.egg-info/SOURCES.txt
suds_jurko_requests.egg-info/dependency_links.txt
suds_jurko_requests.egg-info/requires.txt
suds_jurko_requests.egg-info/top_level.txt
suds_requests/__init__.py