Metadata-Version: 1.1
Name: suds-jurko-requests
Version: 1.2
Summary: suds_requests
